priority_expiry_cache-0.1.0.dist-info/METADATA
priority_expiry_cache-0.1.0.dist-info/WHEEL
priority_expiry_cache/__init__.py
priority_expiry_cache/priority_expiry_cache.cpython-312-darwin.so
priority_expiry_cache-0.1.0.dist-info/RECORD
