Metadata-Version: 2.1
Name: priority-expiry-cache
Version: 0.1.0
Classifier: Programming Language :: Rust
Classifier: Programming Language :: Python :: Implementation :: CPython
Classifier: Programming Language :: Python :: Implementation :: PyPy
Requires-Dist: pytest ; extra == 'tests'
Requires-Dist: version ; extra == 'dynamic'
Provides-Extra: tests
Provides-Extra: dynamic
Requires-Python: >=3.8
